inout_scan/__init__.py
inout_scan/cli.py
inout_scan/inout_scan.py
inout_scan-0.2.2.dist-info/LICENSE
inout_scan-0.2.2.dist-info/METADATA
inout_scan-0.2.2.dist-info/WHEEL
inout_scan-0.2.2.dist-info/entry_points.txt
inout_scan-0.2.2.dist-info/top_level.txt
inout_scan-0.2.2.dist-info/RECORD
