Metadata-Version: 2.1
Name: inout-scan
Version: 0.2.2
Summary: Bar code / RFID interface for InOut
Home-page: https://github.com/brammeleman/inout_scan
Author: Bram Daams
Author-email: b.daams@science.ru.nl
License: GNU General Public License v3
Keywords: inout_scan
Platform: UNKNOWN
Classifier: Development Status :: 2 - Pre-Alpha
Classifier: Intended Audience :: Developers
Classifier: License :: OSI Approved :: GNU General Public License v3 (GPLv3)
Classifier: Natural Language :: English
Classifier: Programming Language :: Python :: 3
Classifier: Programming Language :: Python :: 3.5
Classifier: Programming Language :: Python :: 3.6
Classifier: Programming Language :: Python :: 3.7
Classifier: Programming Language :: Python :: 3.8
Requires-Python: >=3.5
Requires-Dist: Click (>=7.0)
Requires-Dist: pyserial
Requires-Dist: requests
